MANIFEST.in
MakeDoc
RMS.py
cep.py
dyn_prog_pitch.py
emphasis_stevens.py
epydoc.config
feature_vec.py
foo.py
irregularity.py
pdur.py
peakiness.py
probe_feature_vec.py
setup.py
show_feature_vec.py
xform_feature_vec.py
lib/__init__.py
lib/hpfilter.py
lib/percep_spec.py
lib/power.py
lib/voice_misc.py
voicing.egg-info/PKG-INFO
voicing.egg-info/SOURCES.txt
voicing.egg-info/dependency_links.txt
voicing.egg-info/requires.txt
voicing.egg-info/top_level.txt