Metadata-Version: 1.0
Name: voicing
Version: 1.0.0
Summary: Python Libraries and scripts for speech analysis.
Home-page: http://kochanski.org/gpk/code/speechresearch/voicing
Author: Greg Kochanski
Author-email: gpk@kochanski.org
License: GPL2
Keywords: phonetics speech computation linguistics scripts library python science perception feature vector loudness spectral slope
Platform: All
Classifier: License :: OSI Approved :: GNU General Public License (GPL)
Classifier: Operating System :: OS Independent
Classifier: Development Status :: 3 - Alpha
Classifier: Topic :: Scientific/Engineering
Classifier: Environment :: Console
Classifier: Intended Audience :: Science/Research
Classifier: Programming Language :: Python
Classifier: Operating System :: OS Independent
Classifier: Programming Language :: Python
